korean_rule_helper/__init__.py
korean_rule_helper/config.py
korean_rule_helper/josa_helper.py
korean_rule_helper/korean_rule_helper.py
korean_rule_helper/korean_sentence.py
korean_rule_helper/rule.py
korean_rule_helper/parser/__init__.py
korean_rule_helper/parser/mecab.py
korean_rule_helper/parser/parser.py
korean_rule_helper/parser/tag.py
korean_rule_helper-0.0.8.dist-info/METADATA
korean_rule_helper-0.0.8.dist-info/WHEEL
korean_rule_helper-0.0.8.dist-info/top_level.txt
korean_rule_helper-0.0.8.dist-info/RECORD
