Metadata-Version: 2.1
Name: korean-rule-helper
Version: 0.0.8
Summary: 한국어 rule-based 처리를 간단히
Home-page: https://github.com/5yearsKim/KoreanRuleHelper
Author: 5yearsKim
Author-email: hypothesis22@gmail.com
Requires-Dist: hgtk (==0.1.3)
Requires-Dist: six (==1.16.0)
Requires-Dist: mecab-ko (==1.0.0)
